archaea_simulation/__init__.py
archaea_simulation/bes/create_idf.py
archaea_simulation/bes/honeybee-openstudio-0.0.0.gem
archaea_simulation/bes/material/construction_set.py
archaea_simulation/bes/material/material_set.py
archaea_simulation/bes/schedule/activity_rule_set.py
archaea_simulation/bes/schedule/activity_rule_set2.py
archaea_simulation/bes/schedule/air_velocity_rule_set.py
archaea_simulation/bes/schedule/ankle_level_air_velocity_rule_set.py
archaea_simulation/bes/schedule/clothing_insulation_rule_set.py
archaea_simulation/bes/schedule/comfort_calculations_rule_set.py
archaea_simulation/bes/schedule/equipment_rule_set.py
archaea_simulation/bes/schedule/equipment_rule_set2.py
archaea_simulation/bes/schedule/generator.py
archaea_simulation/bes/schedule/hvac_rule_set.py
archaea_simulation/bes/schedule/infiltration_rule_set.py
archaea_simulation/bes/schedule/lighting_rule_set.py
archaea_simulation/bes/schedule/lighting_rule_set2.py
archaea_simulation/bes/schedule/occupancy_rule_set.py
archaea_simulation/bes/schedule/occupancy_rule_set2.py
archaea_simulation/bes/schedule/program_types copy.py
archaea_simulation/bes/schedule/program_types.py
archaea_simulation/bes/schedule/program_types2.py
archaea_simulation/bes/schedule/type_limits.py
archaea_simulation/bes/static_constants.py
archaea_simulation/cfd/__init__.py
archaea_simulation/cfd/case/0/U
archaea_simulation/cfd/case/0/epsilon
archaea_simulation/cfd/case/0/k
archaea_simulation/cfd/case/0/nut
archaea_simulation/cfd/case/0/p
archaea_simulation/cfd/case/Allclean
archaea_simulation/cfd/case/Allrun
archaea_simulation/cfd/case/constant/momentumTransport
archaea_simulation/cfd/case/constant/transportProperties
archaea_simulation/cfd/case/system/blockMeshDict
archaea_simulation/cfd/case/system/controlDict
archaea_simulation/cfd/case/system/cutPlaneSurface
archaea_simulation/cfd/case/system/decomposeParDict
archaea_simulation/cfd/case/system/fvSchemes
archaea_simulation/cfd/case/system/fvSolution
archaea_simulation-1.3.0.dist-info/LICENSE
archaea_simulation-1.3.0.dist-info/LICENSE.txt
archaea_simulation-1.3.0.dist-info/METADATA
archaea_simulation-1.3.0.dist-info/WHEEL
archaea_simulation-1.3.0.dist-info/RECORD
