Metadata-Version: 2.1
Name: archaea-simulation
Version: 1.3.0
Summary: Wrapper definitions for simulation tools.
Home-page: https://github.com/archaeans/archaea-simulation
License: Apache-2.0
Keywords: geometry,simulation
Author: Oğuzhan Koral
Author-email: oguzhankoral@gmail.com
Requires-Python: >=3.10,<4.0
Classifier: Development Status :: 3 - Alpha
Classifier: Intended Audience :: Developers
Classifier: Intended Audience :: Science/Research
Classifier: License :: OSI Approved :: Apache Software License
Classifier: Programming Language :: Python :: 3
Classifier: Programming Language :: Python :: 3.10
Classifier: Programming Language :: Python :: 3.11
Classifier: Programming Language :: Python :: 3.12
Classifier: Topic :: Scientific/Engineering :: Mathematics
Requires-Dist: archaea (==1.1.28)
Requires-Dist: honeybee-energy (>=1.105.15,<2.0.0)
Requires-Dist: specklepy (>=2.21.2,<3.0.0)
Requires-Dist: vtk (>=9.2.6,<10.0.0)
Project-URL: Repository, https://github.com/archaeans/archaea-simulation
